onpy/__init__.py
onpy/client.py
onpy/document.py
onpy/part.py
onpy/api/__init__.py
onpy/api/endpoints.py
onpy/api/rest_api.py
onpy/api/schema.py
onpy/api/versioning.py
onpy/elements/__init__.py
onpy/elements/assembly.py
onpy/elements/base.py
onpy/elements/partstudio.py
onpy/entities/__init__.py
onpy/entities/entities.py
onpy/entities/filter.py
onpy/entities/protocols.py
onpy/entities/queries.py
onpy/features/__init__.py
onpy/features/base.py
onpy/features/extrude.py
onpy/features/loft.py
onpy/features/planes.py
onpy/features/translate.py
onpy/features/sketch/__init__.py
onpy/features/sketch/sketch.py
onpy/features/sketch/sketch_items.py
onpy/util/__init__.py
onpy/util/credentials.py
onpy/util/exceptions.py
onpy/util/misc.py
onpy-0.0.7.dist-info/METADATA
onpy-0.0.7.dist-info/WHEEL
onpy-0.0.7.dist-info/licenses/LICENSE
onpy-0.0.7.dist-info/RECORD
