Metadata-Version: 2.4
Name: onpy
Version: 0.0.7
Summary: A Python API for building models in OnShape
Author-email: Kyle Tennison <kyletennison@gmail.com>
Maintainer-email: Kyle Tennison <kyletennison@gmail.com>
License: Copyright 2024 Kyle Tennison
License-File: LICENSE
Classifier: Programming Language :: Python
Requires-Python: >=3.12
Requires-Dist: loguru
Requires-Dist: numpy
Requires-Dist: prettytable
Requires-Dist: pydantic
Requires-Dist: requests
Provides-Extra: dev
Requires-Dist: nbconvert; extra == 'dev'
Requires-Dist: pyright; extra == 'dev'
Requires-Dist: pytest; extra == 'dev'
Requires-Dist: ruff; extra == 'dev'
Requires-Dist: types-requests; extra == 'dev'
